[
  {
    "path": "public/assets/uploads/image1.jpg",
    "is_video": 0
  },
  {
    "path": "https://www.youtube.com/watch?v=example1",
    "is_video": 1
  },
  {
    "path": "public/assets/uploads/image2.jpg",
    "is_video": 0
  },
  {
    "path": "https://www.youtube.com/watch?v=example2",
    "is_video": 1
  },
  {
    "path": "public/assets/uploads/image3.jpg",
    "is_video": 0
  },
  {
    "path": "https://www.youtube.com/watch?v=example3",
    "is_video": 1
  },
  {
    "path": "public/assets/uploads/image4.jpg",
    "is_video": 0
  },
  {
    "path": "public/assets/uploads/image5.jpg",
    "is_video": 0
  },
  {
    "path": "https://www.youtube.com/watch?v=example4",
    "is_video": 1
  },
  {
    "path": "https://www.youtube.com/watch?v=example5",
    "is_video": 1
  },
  {
    "path": "public/assets/uploads/image6.jpg",
    "is_video": 0
  },
  {
    "path": "public/assets/uploads/image7.jpg",
    "is_video": 0
  }
]
